src/memory.sv
// memory.sv

module memory #(
    parameter WORDS = 64,
    parameter mem_init = ""
) (
    input logic clk,
    input logic [31:0] address,
    input logic [31:0] write_data,
    input logic write_enable,
    input logic rst_n,

    output logic [31:0] read_data
);

/*
* This memory is byte addressed
* But have no support for mis-aligned write nor reads.
*/

reg [31:0] mem [0:WORDS-1];  // Memory array of words (32-bits)

initial begin
    $readmemh(mem_init, mem);
end

always @(posedge clk) begin
    // reset logic
    if (rst_n == 1'b0) begin
        for (int i = 0; i < WORDS; i++) begin
            mem[i] <= 32'b0;  
        end
    end
    else if (write_enable) begin
        // Ensure the address is aligned to a word boundary
        // If not, we ignore the write
        if (address[1:0] == 2'b00) begin 
            //here, address[31:2] is the word index
            mem[address[7:2]] <= write_data;
        end
    end
end

// Read logic
always_comb begin
    //here, address[31:2] is the word index
    read_data = mem[address[7:2]]; 
end

endmodule

src/alu.sv
module alu (
    input logic [2:0] alu_control,
    input logic [31:0] src1,
    input logic [31:0] src2,

    output logic [31:0] alu_result,
    output logic zero


);

always_comb begin
    case (alu_control)
        3'b000 : alu_result =src1 + src2;
        3'b010 : alu_result = src1 & src2;
        3'b011 : alu_result = src1 | src2;
        3'b001 : alu_result = src1 + (~src2 + 1'b1); // new subtraction command 
        default : alu_result = 32'b0;

    endcase
end

assign zero = alu_result == 32'b0;


endmodule

src/signext.sv
module signext(
    input logic [24:0] raw_src,
    input logic [1:0] imm_source,

    output logic [31:0] immediate

);

logic [11:0] gathered_imm;


always_comb begin
    case (imm_source)
        2'b00: gathered_imm = raw_src[24:13];
        2'b01: gathered_imm = {raw_src[24:18], raw_src[4:0]};
        2'b10 : gathered_imm = {raw_src[0], raw_src[23:18], raw_src[4:1], 1'b0};
        default: gathered_imm = 12'b0;

    endcase
end

assign immediate = (imm_source == 2'b10) ? {{20{raw_src[24]}}, gathered_imm} : 
                    {{20{gathered_imm[11]}}, gathered_imm};

endmodule

src/regfile.sv
// regfile.sv

module regfile (
    // basic signals
    input logic clk,
    input logic rst_n,

    // Reads
    input logic [4:0] address1,
    input logic [4:0] address2,
    output logic [31:0] read_data1,
    output logic [31:0] read_data2,

    // Writes
    input logic write_enable,
    input logic [31:0] write_data,
    input logic [4:0] address3
);

// 32bits register. 32 of them (addressed with 5 bits)
reg [31:0] registers [0:31]; 

// Write logic
always @(posedge clk) begin
    // reset support, init to 0
    if(rst_n == 1'b0) begin
        for(int i = 0; i<32; i++) begin
            registers[i] <= 32'b0;
        end
    end 
    // Write, except on 0, reserved for a zero constant according to RISC-V specs
    else if(write_enable == 1'b1 && address3 != 0) begin
        registers[address3] <= write_data;
    end
end

// Read logic, async
always_comb begin : readLogic
    read_data1 = registers[address1];
    read_data2 = registers[address2];
end


endmodule

src/cu.sv
module control(
    input logic [6:0] op,
    input logic [2:0] func3,
    input logic [6:0] func7,
    input logic alu_zero,

    output logic [2:0] alu_control,
    output logic [1:0] imm_source,
    output logic reg_write,
    output logic mem_write,
    output logic alu_source,
    output logic write_back_source,
    output logic pc_source
);

//main decoder
logic [1:0] alu_op;
logic branch;
always_comb begin
    // prevent latch problem
    reg_write         = 1'b0;
    imm_source        = 2'b00;
    mem_write         = 1'b0;
    alu_op            = 2'b00;
    alu_source        = 1'b0;
    write_back_source = 1'b0;
    branch            = 1'b0;
    // lw command and sw command 
    case(op)
        7'b0000011: begin
            reg_write = 1'b1;
            imm_source = 2'b00;
            mem_write = 1'b0;
            alu_op = 2'b00;
            alu_source = 1'b1;
            write_back_source = 1'b1;
            branch = 1'b0; 
        
        end
        7'b0100011 : begin
            reg_write = 1'b0;
            imm_source = 2'b01;
            mem_write = 1'b1;
            alu_op = 2'b00;
            alu_source = 1'b1;
            branch = 1'b0; 
        end
        // R-type command verification
        7'b0110011 : begin
            reg_write = 1'b1;
            mem_write = 1'b0;
            alu_op = 2'b10;
            alu_source = 1'b0;
            write_back_source = 1'b0;
            branch = 1'b0; 

        end
        // B-type instruction
        7'b1100011 : begin
            reg_write = 1'b0;
            imm_source = 2'b10;
            alu_source = 1'b0;
            mem_write = 1'b0;
            alu_op = 2'b01;
            branch = 1'b1;

        end

        default: begin
            reg_write = 1'b0;
            imm_source = 2'b00;
            mem_write = 1'b0;
            alu_op = 2'b00;
        
        end   
    endcase
end

always_comb begin 
    case(alu_op)
        //lw, sw
        2'b00 : alu_control = 3'b000;
        2'b10 : begin
            case (func3)
                // ADD
                3'b000 : alu_control = 3'b000;
                3'b111 : alu_control = 3'b010;
                3'b110 : alu_control = 3'b011;
                default : alu_control = 3'b111;
            endcase
        end
        // B-type decoder
        2'b01 : alu_control = 3'b001;
        default : alu_control = 3'b111;
    endcase

assign pc_source = branch & alu_zero;

end
endmodule

src/cpu.sv
module cpu (
    input logic clk,
    input logic rst_n

);
// program counter 
reg [31:0] pc;
logic [31:0] pc_next;

always_comb begin : pc_select
    case (pc_source)
        1'b1 : pc_next = pc + immediate; // pc_target
        default: pc_next = pc + 4; // pc + 4
    endcase
end

always @(posedge clk) begin
    if(rst_n == 0) begin
        pc <= 32'b0;
    end else begin
        pc <= pc_next;
    end
end

wire [31:0] instruction;


// instruction memory which acting as ROM 
memory #(
    .mem_init("./test_imemory.hex")

) instruction_memory(
    .clk(clk),
    .address(pc),
    .write_data(32'b0),
    .write_enable(1'b0),
    .rst_n(1'b1),
    // Memory Outputs
    .read_data(instruction)
);

//control unit part, intercept the instruction from the program counter, acting as cu 


logic [6:0] op;
assign op = instruction [6:0];
logic [2:0] f3;
assign f3 = instruction[14:12];
wire alu_zero;
// out of the control unit 
wire [2:0] alu_control;
wire [1:0] imm_source;
wire reg_write;
wire mem_write ;
wire alu_source;
wire write_back_source;
wire pc_source;

control control(
    .op(op),
    .func3(f3),
    .func7(7'b0),
    .alu_zero(alu_zero),

    //output 
    .alu_control(alu_control),
    .reg_write (reg_write),
    .mem_write (mem_write),
    .imm_source (imm_source),
    .alu_source (alu_source),
    .write_back_source (write_back_source),
    .pc_source (pc_source)

);

//regfile 
logic [4:0] source_reg1;
assign source_reg1 = instruction[19:15];
logic [4:0] source_reg2;
assign source_reg2 = instruction[24:20];
logic [4:0] dest_reg;
assign dest_reg = instruction[11:7];
wire [31:0] read_reg1;
wire [31:0] read_reg2;

logic [31:0] write_back_data;
always_comb begin : write_back_source_select
    case (write_back_source)
        1'b1: write_back_data = mem_read;
        default: write_back_data = alu_result;
    endcase
end


regfile regfile(
    //basic signals 
    .clk(clk),
    .rst_n(rst_n),
    //read in 
    .address1(source_reg1),
    .address2(source_reg2),
    //read out 
    .read_data1(read_reg1),
    .read_data2(read_reg2),
    //write in
    .write_enable(reg_write),
    .write_data(write_back_data),
    .address3(dest_reg)

);

// sign ext part 

logic [24:0] raw_imm;
assign raw_imm = instruction[31:7];
wire [31:0] immediate;

signext sign_extender (
    .raw_src (raw_imm),
    .imm_source (imm_source),
    .immediate (immediate)

);

//ALU part 
logic [31:0] alu_src2;
wire [31:0] alu_result;

always_comb begin: alu_source_select
    case(alu_source)
        1'b1 : alu_src2 = immediate;
        default : alu_src2 = read_reg2;
    endcase
end

alu alu_inst (
    .alu_control(alu_control),
    .src1(read_reg1),
    .src2(alu_src2),
    .alu_result(alu_result),
    .zero(alu_zero)

);

// data memory 
wire [31:0] mem_read;

memory #(
    .mem_init ("./test_dmemory.hex")
) data_memory(
 // Memory inputs
    .clk(clk),
    .address(alu_result),
    .write_data(read_reg2),
    .write_enable(mem_write),
    .rst_n(1'b1),

    // Memory outputs
    .read_data(mem_read)
);




endmodule

tb/cpu/dump.vcd
$version Generated by VerilatedVcd $end
$timescale 1ps $end
 $scope module $rootio $end
  $var wire 1 " clk $end
  $var wire 1 # rst_n $end
 $upscope $end
 $scope module cpu $end
  $var wire 1 $ clk $end
  $var wire 1 % rst_n $end
  $var wire 32 & pc [31:0] $end
  $var wire 32 ' pc_next [31:0] $end
  $var wire 32 ( instruction [31:0] $end
  $var wire 7 ) op [6:0] $end
  $var wire 3 * f3 [2:0] $end
  $var wire 1 + alu_zero $end
  $var wire 3 , alu_control [2:0] $end
  $var wire 2 - imm_source [1:0] $end
  $var wire 1 . reg_write $end
  $var wire 1 / mem_write $end
  $var wire 1 0 alu_source $end
  $var wire 1 1 write_back_source $end
  $var wire 1 2 pc_source $end
  $var wire 5 3 source_reg1 [4:0] $end
  $var wire 5 4 source_reg2 [4:0] $end
  $var wire 5 5 dest_reg [4:0] $end
  $var wire 32 6 read_reg1 [31:0] $end
  $var wire 32 7 read_reg2 [31:0] $end
  $var wire 32 8 write_back_data [31:0] $end
  $var wire 25 9 raw_imm [24:0] $end
  $var wire 32 : immediate [31:0] $end
  $var wire 32 ; alu_src2 [31:0] $end
  $var wire 32 < alu_result [31:0] $end
  $var wire 32 = mem_read [31:0] $end
  $scope module alu_inst $end
   $var wire 3 > alu_control [2:0] $end
   $var wire 32 ? src1 [31:0] $end
   $var wire 32 @ src2 [31:0] $end
   $var wire 32 A alu_result [31:0] $end
   $var wire 1 B zero $end
  $upscope $end
  $scope module control $end
   $var wire 7 C op [6:0] $end
   $var wire 3 D func3 [2:0] $end
   $var wire 7 &! func7 [6:0] $end
   $var wire 1 E alu_zero $end
   $var wire 3 F alu_control [2:0] $end
   $var wire 2 G imm_source [1:0] $end
   $var wire 1 H reg_write $end
   $var wire 1 I mem_write $end
   $var wire 1 J alu_source $end
   $var wire 1 K write_back_source $end
   $var wire 1 L pc_source $end
   $var wire 2 M alu_op [1:0] $end
   $var wire 1 N branch $end
  $upscope $end
  $scope module data_memory $end
   $var wire 32 '! WORDS [31:0] $end
   $var wire 144 (! mem_init [143:0] $end
   $var wire 1 O clk $end
   $var wire 32 P address [31:0] $end
   $var wire 32 Q write_data [31:0] $end
   $var wire 1 R write_enable $end
   $var wire 1 -! rst_n $end
   $var wire 32 S read_data [31:0] $end
  $upscope $end
  $scope module instruction_memory $end
   $var wire 32 '! WORDS [31:0] $end
   $var wire 144 .! mem_init [143:0] $end
   $var wire 1 T clk $end
   $var wire 32 U address [31:0] $end
   $var wire 32 3! write_data [31:0] $end
   $var wire 1 4! write_enable $end
   $var wire 1 -! rst_n $end
   $var wire 32 V read_data [31:0] $end
  $upscope $end
  $scope module regfile $end
   $var wire 1 W clk $end
   $var wire 1 X rst_n $end
   $var wire 5 Y address1 [4:0] $end
   $var wire 5 Z address2 [4:0] $end
   $var wire 32 [ read_data1 [31:0] $end
   $var wire 32 \ read_data2 [31:0] $end
   $var wire 1 ] write_enable $end
   $var wire 32 ^ write_data [31:0] $end
   $var wire 5 _ address3 [4:0] $end
   $var wire 32 ` registers[0] [31:0] $end
   $var wire 32 a registers[1] [31:0] $end
   $var wire 32 b registers[2] [31:0] $end
   $var wire 32 c registers[3] [31:0] $end
   $var wire 32 d registers[4] [31:0] $end
   $var wire 32 e registers[5] [31:0] $end
   $var wire 32 f registers[6] [31:0] $end
   $var wire 32 g registers[7] [31:0] $end
   $var wire 32 h registers[8] [31:0] $end
   $var wire 32 i registers[9] [31:0] $end
   $var wire 32 j registers[10] [31:0] $end
   $var wire 32 k registers[11] [31:0] $end
   $var wire 32 l registers[12] [31:0] $end
   $var wire 32 m registers[13] [31:0] $end
   $var wire 32 n registers[14] [31:0] $end
   $var wire 32 o registers[15] [31:0] $end
   $var wire 32 p registers[16] [31:0] $end
   $var wire 32 q registers[17] [31:0] $end
   $var wire 32 r registers[18] [31:0] $end
   $var wire 32 s registers[19] [31:0] $end
   $var wire 32 t registers[20] [31:0] $end
   $var wire 32 u registers[21] [31:0] $end
   $var wire 32 v registers[22] [31:0] $end
   $var wire 32 w registers[23] [31:0] $end
   $var wire 32 x registers[24] [31:0] $end
   $var wire 32 y registers[25] [31:0] $end
   $var wire 32 z registers[26] [31:0] $end
   $var wire 32 { registers[27] [31:0] $end
   $var wire 32 | registers[28] [31:0] $end
   $var wire 32 } registers[29] [31:0] $end
   $var wire 32 ~ registers[30] [31:0] $end
   $var wire 32 !! registers[31] [31:0] $end
  $upscope $end
  $scope module sign_extender $end
   $var wire 25 "! raw_src [24:0] $end
   $var wire 2 #! imm_source [1:0] $end
   $var wire 32 $! immediate [31:0] $end
   $var wire 12 %! gathered_imm [11:0] $end
  $upscope $end
 $upscope $end
$enddefinitions $end


#0
1"
0#
1$
0%
b00000000000000000000000000000000 &
b00000000000000000000000000000100 '
b00000000100000000010100100000011 (
b0000011 )
b010 *
0+
b000 ,
b00 -
1.
0/
10
11
02
b00000 3
b01000 4
b10010 5
b00000000000000000000000000000000 6
b00000000000000000000000000000000 7
b11011110101011011011111011101111 8
b0000000010000000001010010 9
b00000000000000000000000000001000 :
b00000000000000000000000000001000 ;
b00000000000000000000000000001000 <
b11011110101011011011111011101111 =
b000 >
b00000000000000000000000000000000 ?
b00000000000000000000000000001000 @
b00000000000000000000000000001000 A
0B
b0000011 C
b010 D
0E
b000 F
b00 G
1H
0I
1J
1K
0L
b00 M
0N
1O
b00000000000000000000000000001000 P
b00000000000000000000000000000000 Q
0R
b11011110101011011011111011101111 S
1T
b00000000000000000000000000000000 U
b00000000100000000010100100000011 V
1W
0X
b00000 Y
b01000 Z
b00000000000000000000000000000000 [
b00000000000000000000000000000000 \
1]
b11011110101011011011111011101111 ^
b10010 _
b00000000000000000000000000000000 `
b00000000000000000000000000000000 a
b00000000000000000000000000000000 b
b00000000000000000000000000000000 c
b00000000000000000000000000000000 d
b00000000000000000000000000000000 e
b00000000000000000000000000000000 f
b00000000000000000000000000000000 g
b00000000000000000000000000000000 h
b00000000000000000000000000000000 i
b00000000000000000000000000000000 j
b00000000000000000000000000000000 k
b00000000000000000000000000000000 l
b00000000000000000000000000000000 m
b00000000000000000000000000000000 n
b00000000000000000000000000000000 o
b00000000000000000000000000000000 p
b00000000000000000000000000000000 q
b00000000000000000000000000000000 r
b00000000000000000000000000000000 s
b00000000000000000000000000000000 t
b00000000000000000000000000000000 u
b00000000000000000000000000000000 v
b00000000000000000000000000000000 w
b00000000000000000000000000000000 x
b00000000000000000000000000000000 y
b00000000000000000000000000000000 z
b00000000000000000000000000000000 {
b00000000000000000000000000000000 |
b00000000000000000000000000000000 }
b00000000000000000000000000000000 ~
b00000000000000000000000000000000 !!
b0000000010000000001010010 "!
b00 #!
b00000000000000000000000000001000 $!
b000000001000 %!
b0000000 &!
b00000000000000000000000001000000 '!
b001011100010111101110100011001010111001101110100010111110110010001101101011001010110110101101111011100100111100100101110011010000110010101111000 (!
1-!
b001011100010111101110100011001010111001101110100010111110110100101101101011001010110110101101111011100100111100100101110011010000110010101111000 .!
b00000000000000000000000000000000 3!
04!
#500
0"
0$
0O
0T
0W
#1000
1"
1#
1$
1%
1O
1T
1W
1X
#1500
0"
0$
0O
0T
0W
#2000
1"
1$
b00000000000000000000000000000100 &
b00000000000000000000000000001000 '
b00000001001000000010011000100011 (
b0100011 )
b01 -
0.
1/
01
b10010 4
b01100 5
b11011110101011011011111011101111 7
b00000000000000000000000000001100 8
b0000000100100000001001100 9
b00000000000000000000000000001100 :
b00000000000000000000000000001100 ;
b00000000000000000000000000001100 <
b11110010111100101111001011110010 =
b00000000000000000000000000001100 @
b00000000000000000000000000001100 A
b0100011 C
b01 G
0H
1I
0K
1O
b00000000000000000000000000001100 P
b11011110101011011011111011101111 Q
1R
b11110010111100101111001011110010 S
1T
b00000000000000000000000000000100 U
b00000001001000000010011000100011 V
1W
b10010 Z
b11011110101011011011111011101111 \
0]
b00000000000000000000000000001100 ^
b01100 _
b11011110101011011011111011101111 r
b0000000100100000001001100 "!
b01 #!
b00000000000000000000000000001100 $!
b000000001100 %!
#2500
0"
0$
0O
0T
0W
#3000
1"
1$
b00000000000000000000000000001000 &
b00000000000000000000000000001100 '
b00000001000000000010100110000011 (
b0000011 )
b00 -
1.
0/
11
b10000 4
b10011 5
b00000000000000000000000000000000 7
b00000000000000000000101010101010 8
b0000000100000000001010011 9
b00000000000000000000000000010000 :
b00000000000000000000000000010000 ;
b00000000000000000000000000010000 <
b00000000000000000000101010101010 =
b00000000000000000000000000010000 @
b00000000000000000000000000010000 A
b0000011 C
b00 G
1H
0I
1K
1O
b00000000000000000000000000010000 P
b00000000000000000000000000000000 Q
0R
b00000000000000000000101010101010 S
1T
b00000000000000000000000000001000 U
b00000001000000000010100110000011 V
1W
b10000 Z
b00000000000000000000000000000000 \
1]
b00000000000000000000101010101010 ^
b10011 _
b0000000100000000001010011 "!
b00 #!
b00000000000000000000000000010000 $!
b000000010000 %!
#3500
0"
0$
0O
0T
0W
#4000
1"
1$
b00000000000000000000000000001100 &
b00000000000000000000000000010000 '
b00000001001110010000101000110011 (
b0110011 )
b000 *
00
01
b10010 3
b10011 4
b10100 5
b11011110101011011011111011101111 6
b00000000000000000000101010101010 7
b11011110101011011100100110011001 8
b0000000100111001000010100 9
b00000000000000000000000000010011 :
b00000000000000000000101010101010 ;
b11011110101011011100100110011001 <
b00000000000000000000000000000000 =
b11011110101011011011111011101111 ?
b00000000000000000000101010101010 @
b11011110101011011100100110011001 A
b0110011 C
b000 D
0J
0K
b10 M
1O
b11011110101011011100100110011001 P
b00000000000000000000101010101010 Q
b00000000000000000000000000000000 S
1T
b00000000000000000000000000001100 U
b00000001001110010000101000110011 V
1W
b10010 Y
b10011 Z
b11011110101011011011111011101111 [
b00000000000000000000101010101010 \
b11011110101011011100100110011001 ^
b10100 _
b00000000000000000000101010101010 s
b0000000100111001000010100 "!
b00000000000000000000000000010011 $!
b000000010011 %!
#4500
0"
0$
0O
0T
0W
#5000
1"
1$
b00000000000000000000000000010000 &
b00000000000000000000000000010100 '
b00000001010010010111101010110011 (
b111 *
b010 ,
b10100 4
b10101 5
b11011110101011011100100110011001 7
b11011110101011011000100010001001 8
b0000000101001001011110101 9
b00000000000000000000000000010100 :
b11011110101011011100100110011001 ;
b11011110101011011000100010001001 <
b010 >
b11011110101011011100100110011001 @
b11011110101011011000100010001001 A
b111 D
b010 F
1O
b11011110101011011000100010001001 P
b11011110101011011100100110011001 Q
1T
b00000000000000000000000000010000 U
b00000001010010010111101010110011 V
1W
b10100 Z
b11011110101011011100100110011001 \
b11011110101011011000100010001001 ^
b10101 _
b11011110101011011100100110011001 t
b0000000101001001011110101 "!
b00000000000000000000000000010100 $!
b000000010100 %!
#5500
0"
0$
0O
0T
0W
#6000
1"
1$
b00000000000000000000000000010100 &
b00000000000000000000000000011000 '
b00000001010000000010001010000011 (
b0000011 )
b010 *
b000 ,
10
11
b00000 3
b00101 5
b00000000000000000000000000000000 6
b00010010010111110101010100101101 8
b0000000101000000001000101 9
b00000000000000000000000000010100 ;
b00000000000000000000000000010100 <
b00010010010111110101010100101101 =
b000 >
b00000000000000000000000000000000 ?
b00000000000000000000000000010100 @
b00000000000000000000000000010100 A
b0000011 C
b010 D
b000 F
1J
1K
b00 M
1O
b00000000000000000000000000010100 P
b00010010010111110101010100101101 S
1T
b00000000000000000000000000010100 U
b00000001010000000010001010000011 V
1W
b00000 Y
b00000000000000000000000000000000 [
b00010010010111110101010100101101 ^
b00101 _
b11011110101011011000100010001001 u
b0000000101000000001000101 "!
#6500
0"
0$
0O
0T
0W
#7000
1"
1$
b00000000000000000000000000011000 &
b00000000000000000000000000011100 '
b00000001100000000010001100000011 (
b11000 4
b00110 5
b00000000000000000000000000000000 7
b01111111010011111101010001101010 8
b0000000110000000001000110 9
b00000000000000000000000000011000 :
b00000000000000000000000000011000 ;
b00000000000000000000000000011000 <
b01111111010011111101010001101010 =
b00000000000000000000000000011000 @
b00000000000000000000000000011000 A
1O
b00000000000000000000000000011000 P
b00000000000000000000000000000000 Q
b01111111010011111101010001101010 S
1T
b00000000000000000000000000011000 U
b00000001100000000010001100000011 V
1W
b11000 Z
b00000000000000000000000000000000 \
b01111111010011111101010001101010 ^
b00110 _
b00010010010111110101010100101101 e
b0000000110000000001000110 "!
b00000000000000000000000000011000 $!
b000000011000 %!
#7500
0"
0$
0O
0T
0W
#8000
1"
1$
b00000000000000000000000000011100 &
b00000000000000000000000000100000 '
b00000000011000101110001110110011 (
b0110011 )
b110 *
b011 ,
00
01
b00101 3
b00110 4
b00111 5
b00010010010111110101010100101101 6
b01111111010011111101010001101010 7
b01111111010111111101010101101111 8
b0000000001100010111000111 9
b00000000000000000000000000000110 :
b01111111010011111101010001101010 ;
b01111111010111111101010101101111 <
b00000000000000000000000000000000 =
b011 >
b00010010010111110101010100101101 ?
b01111111010011111101010001101010 @
b01111111010111111101010101101111 A
b0110011 C
b110 D
b011 F
0J
0K
b10 M
1O
b01111111010111111101010101101111 P
b01111111010011111101010001101010 Q
b00000000000000000000000000000000 S
1T
b00000000000000000000000000011100 U
b00000000011000101110001110110011 V
1W
b00101 Y
b00110 Z
b00010010010111110101010100101101 [
b01111111010011111101010001101010 \
b01111111010111111101010101101111 ^
b00111 _
b01111111010011111101010001101010 f
b0000000001100010111000111 "!
b00000000000000000000000000000110 $!
b000000000110 %!
#8500
0"
0$
0O
0T
0W
#9000
1"
1$
b00000000000000000000000000100000 &
b00000000000000000000000000100100 '
b00000000011100110000011001100011 (
b1100011 )
b000 *
b001 ,
b10 -
0.
b00110 3
b00111 4
b01100 5
b01111111010011111101010001101010 6
b01111111010111111101010101101111 7
b11111111111011111111111011111011 8
b0000000001110011000001100 9
b00000000000000000000000000001100 :
b01111111010111111101010101101111 ;
b11111111111011111111111011111011 <
b001 >
b01111111010011111101010001101010 ?
b01111111010111111101010101101111 @
b11111111111011111111111011111011 A
b1100011 C
b000 D
b001 F
b10 G
0H
b01 M
1N
1O
b11111111111011111111111011111011 P
b01111111010111111101010101101111 Q
1T
b00000000000000000000000000100000 U
b00000000011100110000011001100011 V
1W
b00110 Y
b00111 Z
b01111111010011111101010001101010 [
b01111111010111111101010101101111 \
0]
b11111111111011111111111011111011 ^
b01100 _
b01111111010111111101010101101111 g
b0000000001110011000001100 "!
b10 #!
b00000000000000000000000000001100 $!
b000000001100 %!
#9500
0"
0$
0O
0T
0W
#10000
1"
1$
b00000000000000000000000000100100 &
b00000000000000000000000000101000 '
b00000000100000000010101100000011 (
b0000011 )
b010 *
b000 ,
b00 -
1.
10
11
b00000 3
b01000 4
b10110 5
b00000000000000000000000000000000 6
b00000000000000000000000000000000 7
b11011110101011011011111011101111 8
b0000000010000000001010110 9
b00000000000000000000000000001000 :
b00000000000000000000000000001000 ;
b00000000000000000000000000001000 <
b11011110101011011011111011101111 =
b000 >
b00000000000000000000000000000000 ?
b00000000000000000000000000001000 @
b00000000000000000000000000001000 A
b0000011 C
b010 D
b000 F
b00 G
1H
1J
1K
b00 M
0N
1O
b00000000000000000000000000001000 P
b00000000000000000000000000000000 Q
b11011110101011011011111011101111 S
1T
b00000000000000000000000000100100 U
b00000000100000000010101100000011 V
1W
b00000 Y
b01000 Z
b00000000000000000000000000000000 [
b00000000000000000000000000000000 \
1]
b11011110101011011011111011101111 ^
b10110 _
b0000000010000000001010110 "!
b00 #!
b00000000000000000000000000001000 $!
b000000001000 %!
#10500
0"
0$
0O
0T
0W
#11000
1"
1$
b00000000000000000000000000101000 &
b00000000000000000000000000111000 '
b00000001011010010000100001100011 (
b1100011 )
b000 *
1+
b001 ,
b10 -
0.
00
01
12
b10010 3
b10110 4
b10000 5
b11011110101011011011111011101111 6
b11011110101011011011111011101111 7
b00000000000000000000000000000000 8
b0000000101101001000010000 9
b00000000000000000000000000010000 :
b11011110101011011011111011101111 ;
b00000000000000000000000000000000 <
b10101110101011101010111010101110 =
b001 >
b11011110101011011011111011101111 ?
b11011110101011011011111011101111 @
b00000000000000000000000000000000 A
1B
b1100011 C
b000 D
1E
b001 F
b10 G
0H
0J
0K
1L
b01 M
1N
1O
b00000000000000000000000000000000 P
b11011110101011011011111011101111 Q
b10101110101011101010111010101110 S
1T
b00000000000000000000000000101000 U
b00000001011010010000100001100011 V
1W
b10010 Y
b10110 Z
b11011110101011011011111011101111 [
b11011110101011011011111011101111 \
0]
b00000000000000000000000000000000 ^
b10000 _
b11011110101011011011111011101111 v
b0000000101101001000010000 "!
b10 #!
b00000000000000000000000000010000 $!
b000000010000 %!
#11500
0"
0$
0O
0T
0W
#12000
1"
1$
b00000000000000000000000000111000 &
b00000000000000000000000000111100 '
b00000000000000000010101100000011 (
b0000011 )
b010 *
b000 ,
b00 -
1.
10
11
02
b00000 3
b00000 4
b10110 5
b00000000000000000000000000000000 6
b00000000000000000000000000000000 7
b10101110101011101010111010101110 8
b0000000000000000001010110 9
b00000000000000000000000000000000 :
b00000000000000000000000000000000 ;
b000 >
b00000000000000000000000000000000 ?
b00000000000000000000000000000000 @
b0000011 C
b010 D
b000 F
b00 G
1H
1J
1K
0L
b00 M
0N
1O
b00000000000000000000000000000000 Q
1T
b00000000000000000000000000111000 U
b00000000000000000010101100000011 V
1W
b00000 Y
b00000 Z
b00000000000000000000000000000000 [
b00000000000000000000000000000000 \
1]
b10101110101011101010111010101110 ^
b10110 _
b0000000000000000001010110 "!
b00 #!
b00000000000000000000000000000000 $!
b000000000000 %!
#12500
0"
0$
0O
0T
0W
#13000
1"
1$
b00000000000000000000000000111100 &
b00000000000000000000000000110100 '
b11111111011010110000110011100011 (
b1100011 )
b000 *
b001 ,
b10 -
0.
00
01
12
b10110 3
b10110 4
b11001 5
b10101110101011101010111010101110 6
b10101110101011101010111010101110 7
b00000000000000000000000000000000 8
b1111111101101011000011001 9
b11111111111111111111111111111000 :
b10101110101011101010111010101110 ;
b001 >
b10101110101011101010111010101110 ?
b10101110101011101010111010101110 @
b1100011 C
b000 D
b001 F
b10 G
0H
0J
0K
1L
b01 M
1N
1O
b10101110101011101010111010101110 Q
1T
b00000000000000000000000000111100 U
b11111111011010110000110011100011 V
1W
b10110 Y
b10110 Z
b10101110101011101010111010101110 [
b10101110101011101010111010101110 \
0]
b00000000000000000000000000000000 ^
b11001 _
b10101110101011101010111010101110 v
b1111111101101011000011001 "!
b10 #!
b11111111111111111111111111111000 $!
b111111111000 %!
#13500
0"
0$
0O
0T
0W
#14000
1"
1$
b00000000000000000000000000110100 &
b00000000000000000000000001000000 '
b00000000000000000000011001100011 (
b00000 3
b00000 4
b01100 5
b00000000000000000000000000000000 6
b00000000000000000000000000000000 7
b0000000000000000000001100 9
b00000000000000000000000000001100 :
b00000000000000000000000000000000 ;
b00000000000000000000000000000000 ?
b00000000000000000000000000000000 @
1O
b00000000000000000000000000000000 Q
1T
b00000000000000000000000000110100 U
b00000000000000000000011001100011 V
1W
b00000 Y
b00000 Z
b00000000000000000000000000000000 [
b00000000000000000000000000000000 \
b01100 _
b0000000000000000000001100 "!
b00000000000000000000000000001100 $!
b000000001100 %!
#14500
0"
0$
0O
0T
0W
#15000
1"
1$
b00000000000000000000000001000000 &
b00000000000000000000000001000100 '
b00000000000000000000000000010011 (
b0010011 )
b000 ,
b00 -
02
b00000 5
b0000000000000000000000000 9
b00000000000000000000000000000000 :
b000 >
b0010011 C
b000 F
b00 G
0L
b00 M
0N
1O
1T
b00000000000000000000000001000000 U
b00000000000000000000000000010011 V
1W
b00000 _
b0000000000000000000000000 "!
b00 #!
b00000000000000000000000000000000 $!
b000000000000 %!
#15500
0"
0$
0O
0T
0W
#16000
1"
1$
b00000000000000000000000001000100 &
b00000000000000000000000001001000 '
1O
1T
b00000000000000000000000001000100 U
1W
